jpl.edrn.ldap.sync-2.0.2-py3.11-nspkg.pth
jpl/edrn/ldap/sync/VERSION.txt
jpl/edrn/ldap/sync/__init__.py
jpl/edrn/ldap/sync/allgroup.py
jpl/edrn/ldap/sync/constants.py
jpl/edrn/ldap/sync/crypt.py
jpl/edrn/ldap/sync/groupsync.py
jpl/edrn/ldap/sync/rdf.py
jpl/edrn/ldap/sync/usersync.py
jpl/edrn/ldap/sync/utils.py
jpl.edrn.ldap.sync-2.0.2.dist-info/LICENSE.md
jpl.edrn.ldap.sync-2.0.2.dist-info/METADATA
jpl.edrn.ldap.sync-2.0.2.dist-info/WHEEL
jpl.edrn.ldap.sync-2.0.2.dist-info/entry_points.txt
jpl.edrn.ldap.sync-2.0.2.dist-info/namespace_packages.txt
jpl.edrn.ldap.sync-2.0.2.dist-info/top_level.txt
jpl.edrn.ldap.sync-2.0.2.dist-info/zip-safe
jpl.edrn.ldap.sync-2.0.2.dist-info/RECORD
