Metadata-Version: 2.1
Name: jpl.edrn.ldap.sync
Version: 2.0.2
Summary: LDAP utilities for the Early Detection Research Network Directory
Home-page: https://github.com/EDRN/jpl.edrn.ldap.sync
Author: Sean Kelly
Author-email: kelly@seankelly.biz
License: apache-2.0
Keywords: ldap directory cancer
Classifier: Development Status :: 4 - Beta
Classifier: Environment :: Console
Classifier: Intended Audience :: Developers
Classifier: Intended Audience :: Healthcare Industry
Classifier: License :: OSI Approved :: Apache Software License
Classifier: Operating System :: OS Independent
Classifier: Programming Language :: Python :: 3
Classifier: Topic :: Scientific/Engineering :: Bio-Informatics
Requires-Python: >=3.7
License-File: LICENSE.md
Requires-Dist: python-ldap ~=3.3.1
Requires-Dist: rdflib ~=6.2.0
